fkr.py
fkr_cli-1.0.0.dist-info/licenses/LICENSE
interfaces/__init__.py
interfaces/parser.py
parsers/__init__.py
parsers/csharp_parser.py
parsers/delphi_parser.py
parsers/parser_factory.py
parsers/py_parser.py
providers/ERPProvider.py
providers/__init__.py
providers/provider.py
fkr_cli-1.0.0.dist-info/METADATA
fkr_cli-1.0.0.dist-info/WHEEL
fkr_cli-1.0.0.dist-info/entry_points.txt
fkr_cli-1.0.0.dist-info/top_level.txt
fkr_cli-1.0.0.dist-info/RECORD
